LICENSE
user_role/__init__.py
user_role/admin.py
user_role/apps.py
user_role/backends.py
user_role/forms.py
user_role/managers.py
user_role/migrations/__init__.py
user_role/models.py
user_role/static/permissions.css
user_role/static/permissions.js
user_role/templates/forms/widgets/permission_input.html
user_role/templates/forms/widgets/permission_option.html
user_role/templates/forms/widgets/permissions_select.html
user_role/templates/role/create.html
user_role/templates/role/update.html
user_role/tests.py
user_role/views.py
user_role/widgets.py
django_role-0.1.6.dist-info/LICENSE
django_role-0.1.6.dist-info/METADATA
django_role-0.1.6.dist-info/WHEEL
django_role-0.1.6.dist-info/RECORD
