Metadata-Version: 2.1
Name: django-role
Version: 0.1.6
Summary: Role for django User model
Home-page: https://github.com/isys35/django-role
License: MIT
Keywords: django
Author: isys35
Author-email: isys35@mail.ru
Requires-Python: >=3.10,<4.0
Classifier: License :: OSI Approved :: MIT License
Classifier: Programming Language :: Python :: 3
Classifier: Programming Language :: Python :: 3.10
Classifier: Programming Language :: Python :: 3.11
Requires-Dist: django (>=4.1.7,<5.0.0)
Requires-Dist: django-bootstrap-v5 (>=1.0.11,<2.0.0)
Project-URL: Documentation, https://github.com/isys35/django-role
Project-URL: Repository, https://github.com/isys35/django-role
